wish_log_analysis_api-0.6.28.dist-info/LICENSE
wish_log_analysis_api-0.6.28.dist-info/METADATA
wish_log_analysis_api-0.6.28.dist-info/WHEEL
wish_log_analysis_api-0.6.28.dist-info/entry_points.txt
wish_log_analysis_api/__init__.py
wish_log_analysis_api/app.py
wish_log_analysis_api/config.py
wish_log_analysis_api/core/__init__.py
wish_log_analysis_api/core/analyzer.py
wish_log_analysis_api/graph.py
wish_log_analysis_api/models.py
wish_log_analysis_api/nodes/__init__.py
wish_log_analysis_api/nodes/command_state_classifier.py
wish_log_analysis_api/nodes/log_summarization.py
wish_log_analysis_api/nodes/result_combiner.py
wish_log_analysis_api-0.6.28.dist-info/RECORD
