Metadata-Version: 2.1
Name: wish-log-analysis-api
Version: 0.6.28
Summary: A library and API for analyzing command execution logs
Keywords: wish,llm,ai,shell,log-analysis
Author-Email: Security & Development Lab <lay.sakura+secdevlab@gmail.com>
Maintainer-Email: Sho Nakatani <lay.sakura@gmail.com>
License:                     GNU AFFERO GENERAL PUBLIC LICENSE
Classifier: Development Status :: 4 - Beta
Classifier: Intended Audience :: Developers
Classifier: Programming Language :: Python :: 3
Classifier: Programming Language :: Python :: 3.10
Classifier: Programming Language :: Python :: 3.11
Classifier: Programming Language :: Python :: 3.12
Classifier: Programming Language :: Python :: 3.13
Classifier: Topic :: Software Development :: Libraries
Classifier: Topic :: System :: Shells
Project-URL: Homepage, https://github.com/SecDev-Lab/wish
Project-URL: Documentation, https://github.com/SecDev-Lab/wish
Project-URL: Repository, https://github.com/SecDev-Lab/wish.git
Project-URL: Issues, https://github.com/SecDev-Lab/wish/issues
Requires-Python: >=3.10
Requires-Dist: pydantic>=2.10.6
Requires-Dist: langgraph>=0.3.5
Requires-Dist: langsmith>=0.3.11
Requires-Dist: langchain-openai>=0.3.7
Requires-Dist: langchain-core>=0.3.41
Requires-Dist: langchain>=0.3.20
Requires-Dist: pydantic-settings>=2.8.1
Requires-Dist: tomli>=2.0.0
Requires-Dist: wish-models>=0.4.5
